timmy/__init__.py
timmy/analyze.py
timmy/analyze_health.py
timmy/cli.py
timmy/conf.py
timmy/env.py
timmy/flock.py
timmy/nodes.py
timmy/tools.py
timmy/analyze_modules/__example__.py
timmy/analyze_modules/__init__.py
timmy/analyze_modules/df.py
timmy/analyze_modules/rabbitmq.py
timmy/modules/__init__.py
timmy/modules/fuel.py
timmy/modules/local.py
timmy-1.26.11.dist-info/DESCRIPTION.rst
timmy-1.26.11.dist-info/METADATA
timmy-1.26.11.dist-info/RECORD
timmy-1.26.11.dist-info/WHEEL
timmy-1.26.11.dist-info/entry_points.txt
timmy-1.26.11.dist-info/metadata.json
timmy-1.26.11.dist-info/top_level.txt
timmy_data/__init__.py
timmy_data/config/example.yaml
timmy_data/rq/default.yaml
timmy_data/rq/neutron.yaml
timmy_data/rq/nova.yaml
timmy_data/rq/filelists/etc-aodh
timmy_data/rq/filelists/etc-apache2
timmy_data/rq/filelists/etc-apt
timmy_data/rq/filelists/etc-astute
timmy_data/rq/filelists/etc-astute.yaml
timmy_data/rq/filelists/etc-ceilometer
timmy_data/rq/filelists/etc-centos-release
timmy_data/rq/filelists/etc-ceph
timmy_data/rq/filelists/etc-cinder
timmy_data/rq/filelists/etc-cobbler
timmy_data/rq/filelists/etc-default
timmy_data/rq/filelists/etc-dnsmasq.conf
timmy_data/rq/filelists/etc-fuel
timmy_data/rq/filelists/etc-glance
timmy_data/rq/filelists/etc-haproxy
timmy_data/rq/filelists/etc-heat
timmy_data/rq/filelists/etc-hiera
timmy_data/rq/filelists/etc-ironic
timmy_data/rq/filelists/etc-keystone
timmy_data/rq/filelists/etc-libvirt
timmy_data/rq/filelists/etc-lsb-release
timmy_data/rq/filelists/etc-mcollective
timmy_data/rq/filelists/etc-mysql
timmy_data/rq/filelists/etc-nailgun
timmy_data/rq/filelists/etc-network
timmy_data/rq/filelists/etc-neutron
timmy_data/rq/filelists/etc-nova
timmy_data/rq/filelists/etc-redhat-release
timmy_data/rq/filelists/etc-resolv.conf
timmy_data/rq/filelists/etc-swift
timmy_data/rq/filelists/etc-sysconfig
timmy_data/rq/filelists/etc-yum
timmy_data/rq/filelists/etc-yum-d
timmy_data/rq/filelists/root-.ks
timmy_data/rq/filelists/root-.log
timmy_data/rq/filelists/root-anaconda
timmy_data/rq/filelists/root-ceph
timmy_data/rq/filelists/var-lib-cloud
timmy_data/rq/filelists/var-lib-puppet-state-last_run_summary.yaml
