Metadata-Version: 2.0
Name: timmy
Version: 1.26.11
Summary: Mirantis OpenStack Ansible-like tool for parallel node operations: two-way data transfer, log collection, remote command execution
Home-page: https://github.com/adobdin/timmy
Author: Aleksandr Dobdin
Author-email: dobdin@gmail.com
License: Apache2
Platform: UNKNOWN
Requires-Dist: pyyaml
